rapid_videocr/__init__.py
rapid_videocr/export.py
rapid_videocr/main.py
rapid_videocr/ocr_processor.py
rapid_videocr/vsf_cli.py
rapid_videocr/vsf_ocr_cli.py
rapid_videocr/utils/__init__.py
rapid_videocr/utils/crop_by_project.py
rapid_videocr/utils/logger.py
rapid_videocr/utils/utils.py
rapid_videocr-3.1.1.dist-info/LICENSE
rapid_videocr-3.1.1.dist-info/METADATA
rapid_videocr-3.1.1.dist-info/WHEEL
rapid_videocr-3.1.1.dist-info/entry_points.txt
rapid_videocr-3.1.1.dist-info/top_level.txt
rapid_videocr-3.1.1.dist-info/RECORD
