Metadata-Version: 2.1
Name: rapid-videocr
Version: 3.1.1
Summary: Tool for extracting hard subtitles from videos.
Home-page: https://github.com/SWHL/RapidVideOCR.git
Author: SWHL
Author-email: liekkaskono@163.com
License: Apache-2.0
Keywords: rapidocr,videocr,subtitle
Platform: Any
Classifier: Programming Language :: Python :: 3.6
Classifier: Programming Language :: Python :: 3.7
Classifier: Programming Language :: Python :: 3.8
Classifier: Programming Language :: Python :: 3.9
Classifier: Programming Language :: Python :: 3.10
Classifier: Programming Language :: Python :: 3.11
Classifier: Programming Language :: Python :: 3.12
Classifier: Programming Language :: Python :: 3.13
Requires-Python: >=3.6
License-File: LICENSE
Requires-Dist: colorlog
Requires-Dist: onnxruntime
Requires-Dist: rapidocr
Requires-Dist: tqdm
